<items>
   <Item ID="brick">
      <count>0</count>
      <Name>
         <entry lang="English">Brick</entry>
         <entry lang="German">Ziegel</entry>
      </Name>
      <type>Build</type>
      <decays>-1</decays>
   </Item>
   <Item ID="glas">
      <count>0</count>
      <Name>
         <entry lang="English">Glas</entry>
         <entry lang="German">Glass</entry>
      </Name>
      <type>Build</type>
      <decays>-1</decays>
   </Item>
   <Item ID="luxurywood">
      <count>0</count>
      <Name>
         <entry lang="English">Luxury Wood</entry>
         <entry lang="German">Luxusholz</entry>
      </Name>
      <type>Build</type>
      <decays>-1</decays>
   </Item>
   <Item ID="marble">
      <count>0</count>
      <Name>
         <entry lang="English">Marble</entry>
         <entry lang="German">Marmor</entry>
      </Name>
      <type>Build</type>
      <decays>-1</decays>
   </Item>
   <Item ID="stone">
      <count>0</count>
      <Name>
         <entry lang="English">Stone</entry>
         <entry lang="German">Stein</entry>
      </Name>
      <type>Build</type>
      <decays>-1</decays>
   </Item>
   <Item ID="tools">
      <count>0</count>
      <Name>
         <entry lang="English">Tools</entry>
         <entry lang="German">Werkzeug</entry>
      </Name>
      <type>Build</type>
      <decays>-1</decays>
   </Item>
   <Item ID="wood">
      <count>0</count>
      <Name>
         <entry lang="English">Wood</entry>
         <entry lang="German">Holz</entry>
      </Name>
      <type>Build</type>
      <decays>-1</decays>
   </Item>
   <Item ID="armors">
      <count>0</count>
      <Name>
         <entry lang="English">Armors</entry>
         <entry lang="German">Rüstungen</entry>
      </Name>
      <type>Intermediate</type>
      <decays>-1</decays>
   </Item>
   <Item ID="beeswax">
      <count>0</count>
      <Name>
         <entry lang="English">Beeswax</entry>
         <entry lang="German">Bienenwachs</entry>
      </Name>
      <type>Intermediate</type>
      <decays>-1</decays>
   </Item>
   <Item ID="bows">
      <count>0</count>
      <Name>
         <entry lang="English">Bows</entry>
         <entry lang="German">Bögen</entry>
      </Name>
      <type>Intermediate</type>
      <decays>-1</decays>
   </Item>
   <Item ID="candles">
      <count>0</count>
      <Name>
         <entry lang="English">Candles</entry>
         <entry lang="German">Kerzen</entry>
      </Name>
      <type>Intermediate</type>
      <decays>-1</decays>
   </Item>
   <Item ID="cannons">
      <count>0</count>
      <Name>
         <entry lang="English">Cannons</entry>
         <entry lang="German">Kanonen</entry>
      </Name>
      <type>Intermediate</type>
      <decays>-1</decays>
   </Item>
   <Item ID="casks">
      <count>0</count>
      <Name>
         <entry lang="English">Casks</entry>
         <entry lang="German">Fässer</entry>
      </Name>
      <type>Intermediate</type>
      <decays>-1</decays>
   </Item>
   <Item ID="clay">
      <count>0</count>
      <Name>
         <entry lang="English">Clay</entry>
         <entry lang="German">Lehm</entry>
      </Name>
      <type>Intermediate</type>
      <decays>-1</decays>
   </Item>
   <Item ID="coal">
      <count>0</count>
      <Name>
         <entry lang="English">Coal</entry>
         <entry lang="German">Kohle</entry>
      </Name>
      <type>Intermediate</type>
      <decays>-1</decays>
   </Item>
   <Item ID="cocoa">
      <count>0</count>
      <Name>
         <entry lang="English">Cocoa</entry>
         <entry lang="German">Kakao</entry>
      </Name>
      <type>Intermediate</type>
      <decays>-1</decays>
   </Item>
   <Item ID="coffeebeans">
      <count>0</count>
      <Name>
         <entry lang="English">Coffee Beans</entry>
         <entry lang="German">Kaffeebohnen</entry>
      </Name>
      <type>Intermediate</type>
      <decays>-1</decays>
   </Item>
   <Item ID="color">
      <count>0</count>
      <Name>
         <entry lang="English">Color</entry>
         <entry lang="German">Farbe</entry>
      </Name>
      <type>Intermediate</type>
      <decays>-1</decays>
   </Item>
   <Item ID="cooperore">
      <count>0</count>
      <Name>
         <entry lang="English">Cooper Ore</entry>
         <entry lang="German">Kupfererz</entry>
      </Name>
      <type>Intermediate</type>
      <decays>-1</decays>
   </Item>
   <Item ID="copperingots">
      <count>0</count>
      <Name>
         <entry lang="English">Copper Ingots</entry>
         <entry lang="German">Kupferbarren</entry>
      </Name>
      <type>Intermediate</type>
      <decays>-1</decays>
   </Item>
   <Item ID="cows">
      <count>0</count>
      <Name>
         <entry lang="English">Cows</entry>
         <entry lang="German">Kühe</entry>
      </Name>
      <type>Intermediate</type>
      <decays>-1</decays>
   </Item>
   <Item ID="diamonds">
      <count>0</count>
      <Name>
         <entry lang="English">Diamonds</entry>
         <entry lang="German">Diamanten</entry>
      </Name>
      <type>Intermediate</type>
      <decays>-1</decays>
   </Item>
   <Item ID="flour">
      <count>0</count>
      <Name>
         <entry lang="English">Flour</entry>
         <entry lang="German">Mehl</entry>
      </Name>
      <type>Intermediate</type>
      <decays>-1</decays>
   </Item>
   <Item ID="flowers">
      <count>0</count>
      <Name>
         <entry lang="English">Flowers</entry>
         <entry lang="German">Blumen</entry>
      </Name>
      <type>Intermediate</type>
      <decays>-1</decays>
   </Item>
   <Item ID="fruits">
      <count>0</count>
      <Name>
         <entry lang="English">Fruits</entry>
         <entry lang="German">Früchte</entry>
      </Name>
      <type>Intermediate</type>
      <decays>-1</decays>
   </Item>
   <Item ID="fur">
      <count>0</count>
      <Name>
         <entry lang="English">Fur</entry>
         <entry lang="German">Pelze</entry>
      </Name>
      <type>Intermediate</type>
      <decays>-1</decays>
   </Item>
   <Item ID="goldingots">
      <count>0</count>
      <Name>
         <entry lang="English">Gold Ingots</entry>
         <entry lang="German">Gold</entry>
      </Name>
      <type>Intermediate</type>
      <decays>-1</decays>
   </Item>
   <Item ID="goldore">
      <count>0</count>
      <Name>
         <entry lang="English">Gold Ore</entry>
         <entry lang="German">Goldnuggets</entry>
      </Name>
      <type>Intermediate</type>
      <decays>-1</decays>
   </Item>
   <Item ID="grainsalt">
      <count>0</count>
      <Name>
         <entry lang="English">Grain Salt</entry>
         <entry lang="German">Grobes Salz</entry>
      </Name>
      <type>Intermediate</type>
      <decays>-1</decays>
   </Item>
   <Item ID="hemp">
      <count>0</count>
      <Name>
         <entry lang="English">Hemp</entry>
         <entry lang="German">Hanf</entry>
      </Name>
      <type>Intermediate</type>
      <decays>-1</decays>
   </Item>
   <Item ID="hempfabric">
      <count>0</count>
      <Name>
         <entry lang="English">Hemp Fabric</entry>
         <entry lang="German">Hanfballen</entry>
      </Name>
      <type>Intermediate</type>
      <decays>-1</decays>
   </Item>
   <Item ID="hops">
      <count>0</count>
      <Name>
         <entry lang="English">Hops</entry>
         <entry lang="German">Hopfen</entry>
      </Name>
      <type>Intermediate</type>
      <decays>0</decays>
   </Item>
   <Item ID="horses">
      <count>0</count>
      <Name>
         <entry lang="English">Horses</entry>
         <entry lang="German">Pferden</entry>
      </Name>
      <type>Intermediate</type>
      <decays>-1</decays>
   </Item>
   <Item ID="ironingots">
      <count>0</count>
      <Name>
         <entry lang="English">Iron Ingots</entry>
         <entry lang="German">Eisenrohling</entry>
      </Name>
      <type>Intermediate</type>
      <decays>-1</decays>
   </Item>
   <Item ID="ironore">
      <count>0</count>
      <Name>
         <entry lang="English">Iron Ore</entry>
         <entry lang="German">Eisenerz</entry>
      </Name>
      <type>Intermediate</type>
      <decays>-1</decays>
   </Item>
   <Item ID="leather">
      <count>0</count>
      <Name>
         <entry lang="English">Leather</entry>
         <entry lang="German">Leder</entry>
      </Name>
      <type>Intermediate</type>
      <decays>-1</decays>
   </Item>
   <Item ID="medicinalherbs">
      <count>0</count>
      <Name>
         <entry lang="English">Medicinal Herbs</entry>
         <entry lang="German">Heilkräuter</entry>
      </Name>
      <type>Intermediate</type>
      <decays>-1</decays>
   </Item>
   <Item ID="olives">
      <count>0</count>
      <Name>
         <entry lang="English">Olives</entry>
         <entry lang="German">Oliven</entry>
      </Name>
      <type>Intermediate</type>
      <decays>-1</decays>
   </Item>
   <Item ID="perfumebottle">
      <count>0</count>
      <Name>
         <entry lang="English">Perfume Bottle</entry>
         <entry lang="German">Parfümflaschen</entry>
      </Name>
      <type>Intermediate</type>
      <decays>-1</decays>
   </Item>
   <Item ID="pig">
      <count>0</count>
      <Name>
         <entry lang="English">Pig</entry>
         <entry lang="German">Schwein</entry>
      </Name>
      <type>Intermediate</type>
      <decays>-1</decays>
   </Item>
   <Item ID="pike">
      <count>0</count>
      <Name>
         <entry lang="English">Pike</entry>
         <entry lang="German">Pikes</entry>
      </Name>
      <type>Intermediate</type>
      <decays>-1</decays>
   </Item>
   <Item ID="pork">
      <count>0</count>
      <Name>
         <entry lang="English">Pork</entry>
         <entry lang="German">Schweinefleisch</entry>
      </Name>
      <type>Intermediate</type>
      <decays>-1</decays>
   </Item>
   <Item ID="rifles">
      <count>0</count>
      <Name>
         <entry lang="English">Rifles</entry>
         <entry lang="German">Büchsen</entry>
      </Name>
      <type>Intermediate</type>
      <decays>-1</decays>
   </Item>
   <Item ID="roughdiamonds">
      <count>0</count>
      <Name>
         <entry lang="English">Rough Diamonds</entry>
         <entry lang="German">Rohdiamanten</entry>
      </Name>
      <type>Intermediate</type>
      <decays>-1</decays>
   </Item>
   <Item ID="sand">
      <count>0</count>
      <Name>
         <entry lang="English">Sand</entry>
         <entry lang="German">Sand</entry>
      </Name>
      <type>Intermediate</type>
      <decays>-1</decays>
   </Item>
   <Item ID="sheepwool">
      <count>1</count>
      <Name>
         <entry lang="English">Sheep´s Wool</entry>
         <entry lang="German">Schafswolle</entry>
      </Name>
      <type>Intermediate</type>
      <decays>-1</decays>
   </Item>
   <Item ID="sheepwoolcloth">
      <count>0</count>
      <Name>
         <entry lang="English">Sheep-Wool Cloth</entry>
         <entry lang="German">Schafswolleleinen *1</entry>
      </Name>
      <type>Intermediate</type>
      <decays>-1</decays>
   </Item>
   <Item ID="silk">
      <count>0</count>
      <Name>
         <entry lang="English">Silk</entry>
         <entry lang="German">Seide</entry>
      </Name>
      <type>Intermediate</type>
      <decays>-1</decays>
   </Item>
   <Item ID="sugar">
      <count>0</count>
      <Name>
         <entry lang="English">Sugar</entry>
         <entry lang="German">Zucker</entry>
      </Name>
      <type>Intermediate</type>
      <decays>-1</decays>
   </Item>
   <Item ID="swords">
      <count>0</count>
      <Name>
         <entry lang="English">Swords</entry>
         <entry lang="German">Schwerter</entry>
      </Name>
      <type>Intermediate</type>
      <decays>-1</decays>
   </Item>
   <Item ID="tobacco">
      <count>0</count>
      <Name>
         <entry lang="English">Tobacco</entry>
         <entry lang="German">Tabak</entry>
      </Name>
      <type>Intermediate</type>
      <decays>-1</decays>
   </Item>
   <Item ID="whaleoil">
      <count>0</count>
      <Name>
         <entry lang="English">Whale Oil</entry>
         <entry lang="German">Waltran</entry>
      </Name>
      <type>Intermediate</type>
      <decays>-1</decays>
   </Item>
   <Item ID="wheat">
      <count>0</count>
      <Name>
         <entry lang="English">Wheat</entry>
         <entry lang="German">Getreide</entry>
      </Name>
      <type>Intermediate</type>
      <decays>-1</decays>
   </Item>
   <Item ID="winegrapes">
      <count>0</count>
      <Name>
         <entry lang="English">Wine Grapes</entry>
         <entry lang="German">Weintrauben</entry>
      </Name>
      <type>Intermediate</type>
      <decays>-1</decays>
   </Item>
   <Item ID="beef">
      <count>0</count>
      <Name>
         <entry lang="English">Beef</entry>
         <entry lang="German">Kuhfleisch</entry>
      </Name>
      <type>Luxury</type>
      <decays>-1</decays>
   </Item>
   <Item ID="beer">
      <count>0</count>
      <Name>
         <entry lang="English">Beer</entry>
         <entry lang="German">Bier</entry>
      </Name>
      <type>Luxury</type>
      <decays>0</decays>
   </Item>
   <Item ID="betterclothes">
      <count>0</count>
      <Name>
         <entry lang="English">Better Clothes</entry>
         <entry lang="German">Bessere Kleidung *1</entry>
      </Name>
      <type>Luxury</type>
      <decays>-1</decays>
   </Item>
   <Item ID="books">
      <count>0</count>
      <Name>
         <entry lang="English">Books</entry>
         <entry lang="German">Buch</entry>
      </Name>
      <type>Luxury</type>
      <decays>-1</decays>
   </Item>
   <Item ID="bread">
      <count>0</count>
      <Name>
         <entry lang="English">Bread</entry>
         <entry lang="German">Brot</entry>
      </Name>
      <type>Luxury</type>
      <decays>-1</decays>
   </Item>
   <Item ID="candleholders">
      <count>0</count>
      <Name>
         <entry lang="English">Candleholder</entry>
         <entry lang="German">Kerzenhalter</entry>
      </Name>
      <type>Luxury</type>
      <decays>-1</decays>
   </Item>
   <Item ID="carpets">
      <count>0</count>
      <Name>
         <entry lang="English">Carpets</entry>
         <entry lang="German">Teppiche</entry>
      </Name>
      <type>Luxury</type>
      <decays>-1</decays>
   </Item>
   <Item ID="cheese">
      <count>0</count>
      <Name>
         <entry lang="English">Cheese</entry>
         <entry lang="German">Käse</entry>
      </Name>
      <type>Luxury</type>
      <decays>0</decays>
   </Item>
   <Item ID="coffee">
      <count>0</count>
      <Name>
         <entry lang="English">Coffee</entry>
         <entry lang="German">Kaffee</entry>
      </Name>
      <type>Luxury</type>
      <decays>-1</decays>
   </Item>
   <Item ID="cutlery">
      <count>0</count>
      <Name>
         <entry lang="English">Cutlery</entry>
         <entry lang="German">Besteck</entry>
      </Name>
      <type>Luxury</type>
      <decays>-1</decays>
   </Item>
   <Item ID="fish">
      <count>0</count>
      <Name>
         <entry lang="English">Fish</entry>
         <entry lang="German">Fisch</entry>
      </Name>
      <type>Luxury</type>
      <decays>-1</decays>
   </Item>
   <Item ID="goggles">
      <count>0</count>
      <Name>
         <entry lang="English">Goggles</entry>
         <entry lang="German">Brillen</entry>
      </Name>
      <type>Luxury</type>
      <decays>-1</decays>
   </Item>
   <Item ID="hempclothes">
      <count>0</count>
      <Name>
         <entry lang="English">Hemp Clothes</entry>
         <entry lang="German">Hanfkleidung</entry>
      </Name>
      <type>Luxury</type>
      <decays>-1</decays>
   </Item>
   <Item ID="honey">
      <count>0</count>
      <Name>
         <entry lang="English">Honey</entry>
         <entry lang="German">Honig</entry>
      </Name>
      <type>Luxury</type>
      <decays>-1</decays>
   </Item>
   <Item ID="jewelry">
      <count>0</count>
      <Name>
         <entry lang="English">Jewelry</entry>
         <entry lang="German">Schmuck</entry>
      </Name>
      <type>Luxury</type>
      <decays>-1</decays>
   </Item>
   <Item ID="leathershoes">
      <count>0</count>
      <Name>
         <entry lang="English">Leather Shoes</entry>
         <entry lang="German">Lederschuhe</entry>
      </Name>
      <type>Luxury</type>
      <decays>-1</decays>
   </Item>
   <Item ID="liquor">
      <count>0</count>
      <Name>
         <entry lang="English">Liquor</entry>
         <entry lang="German">Schnaps</entry>
      </Name>
      <type>Luxury</type>
      <decays>-1</decays>
   </Item>
   <Item ID="luxuryclothes">
      <count>0</count>
      <Name>
         <entry lang="English">Luxury Clothes</entry>
         <entry lang="German">Luxuskleider </entry>
      </Name>
      <type>Luxury</type>
      <decays>-1</decays>
   </Item>
   <Item ID="luxurycutlery">
      <count>0</count>
      <Name>
         <entry lang="English">Luxury Cutlery</entry>
         <entry lang="German">Luxusbesteck</entry>
      </Name>
      <type>Luxury</type>
      <decays>-1</decays>
   </Item>
   <Item ID="milk">
      <count>0</count>
      <Name>
         <entry lang="English">Milk</entry>
         <entry lang="German">Milch</entry>
      </Name>
      <type>Luxury</type>
      <decays>0</decays>
   </Item>
   <Item ID="perfume">
      <count>0</count>
      <Name>
         <entry lang="English">Perfume</entry>
         <entry lang="German">Parfum</entry>
      </Name>
      <type>Luxury</type>
      <decays>-1</decays>
   </Item>
   <Item ID="potatoes">
      <count>0</count>
      <Name>
         <entry lang="English">Potatoes</entry>
         <entry lang="German">Kartoffeln</entry>
      </Name>
      <type>Luxury</type>
      <decays>-1</decays>
   </Item>
   <Item ID="ropes">
      <count>0</count>
      <Name>
         <entry lang="English">Ropes</entry>
         <entry lang="German">Seile</entry>
      </Name>
      <type>Luxury</type>
      <decays>-1</decays>
   </Item>
   <Item ID="salt">
      <count>0</count>
      <Name>
         <entry lang="English">Salt</entry>
         <entry lang="German">Salz</entry>
      </Name>
      <type>Luxury</type>
      <decays>-1</decays>
   </Item>
   <Item ID="soap">
      <count>0</count>
      <Name>
         <entry lang="English">Soap</entry>
         <entry lang="German">Seife</entry>
      </Name>
      <type>Luxury</type>
      <decays>-1</decays>
   </Item>
   <Item ID="spice">
      <count>0</count>
      <Name>
         <entry lang="English">Spice</entry>
         <entry lang="German">Gewürz</entry>
      </Name>
      <type>Luxury</type>
      <decays>-1</decays>
   </Item>
   <Item ID="sweets">
      <count>0</count>
      <Name>
         <entry lang="English">Sweets</entry>
         <entry lang="German">Süßigkeiten</entry>
      </Name>
      <type>Luxury</type>
      <decays>-1</decays>
   </Item>
   <Item ID="tobaccoproducts">
      <count>0</count>
      <Name>
         <entry lang="English">Tobacco Products</entry>
         <entry lang="German">Tabakwaren</entry>
      </Name>
      <type>Luxury</type>
      <decays>-1</decays>
   </Item>
   <Item ID="venison">
      <count>0</count>
      <Name>
         <entry lang="English">Venison</entry>
         <entry lang="German">Wildfleisch</entry>
      </Name>
      <type>Luxury</type>
      <decays>-1</decays>
   </Item>
   <Item ID="wine">
      <count>0</count>
      <Name>
         <entry lang="English">Wine</entry>
         <entry lang="German">Wein</entry>
      </Name>
      <type>Luxury</type>
      <decays>-1</decays>
   </Item>
   <Item ID="sail">
      <count>0</count>
      <Name>
         <entry lang="English">Sail</entry>
         <entry lang="German">Seil</entry>
      </Name>
      <type>Military</type>
      <decays>0</decays>
   </Item>
</items>